data_source_local/__init__.py
data_source_local/data_source.py
data_source_local/data_source_constants.py
data_source_local/data_source_enum.py
data_source_local/data_source_field.py
data_source_local/data_source_instance.py
data_source_local/data_source_type.py
data_source_local-0.0.18.dist-info/METADATA
data_source_local-0.0.18.dist-info/WHEEL
data_source_local-0.0.18.dist-info/top_level.txt
data_source_local-0.0.18.dist-info/RECORD
