Metadata-Version: 2.4
Name: data-source-local
Version: 0.0.18
Home-page: https://github.com/circles-zone/data-source-local-python-package
Author: Circles
Author-email: info@circles.ai
Classifier: Programming Language :: Python :: 3
Classifier: Operating System :: OS Independent
Requires-Dist: logger-local>=0.0.60
Requires-Dist: database-mysql-local>=0.0.83
Requires-Dist: language-remote
Dynamic: author
Dynamic: author-email
Dynamic: classifier
Dynamic: description
Dynamic: description-content-type
Dynamic: home-page
Dynamic: requires-dist
